[
  {
    "key": "documentaires",
    "label": "Documentaires",
    "description": "Tous les documentaires",
    "elements": [
      {
        "titre": "documentaire1",
        "blabla": "blabla docu 1",
        "photo": "photo docu 1",
        "book": "BookDocu1"
      },
      {
        "titre": "documentaire2",
        "blabla": "blabla docu 2",
        "photo": "photo docu 2",
        "book": ""
      }
    ]
  },
  {
    "key": "publicités",
    "label": "Publicités",
    "description": "Toutes les publicités",
    "elements": [
      {
        "titre": "Titre Pub 1",
        "blabla": "blabla Pub 1",
        "photo": "photo Pub 1"
      },
      {
        "titre": "Titre Pub 2",
        "blabla": "blabla Pub 2",
        "photo": "photo Pub 2"
      }
    ]
  },
  {
    "key": "motionDesign",
    "label": "Motion Design",
    "description": "Toutes les activité MotionDesign",
    "elements": [
      {
        "titre": "Titre Design 1",
        "blabla": "blabla Design 1",
        "photo": "photo Design 1"
      },
      {
        "titre": "Titre Design 2",
        "blabla": "blabla Design 2",
        "photo": "photo Design 2"
      },
      {
        "titre": "Titre Design 3",
        "blabla": "blabla Design 3",
        "photo": "photo Design 3"
      }
    ]
  }
]
